<?xml version="1.0" encoding="utf-8"?>
<nrml xmlns:gml="http://www.opengis.net/gml" xmlns="http://openquake.org/xmlns/nrml/0.4">
    <simpleFaultRupture>
        <magnitude>6.5</magnitude>
        <rake>90</rake>
        <hypocenter lat="43.28" lon=" 77.2" depth="5"/>
        <simpleFaultGeometry>
            <gml:LineString>
                <gml:posList>
                    77.0414523956 43.2952960164
                    77.054266837 43.2967083692
                    77.0592009162 43.2988206787
                    77.0665672037 43.2989898584
                    77.0692936197 43.3011735204
                    77.0750953075 43.3035385751
                    77.0927763663 43.3037180772
                    77.0959128621 43.3045552594
                    77.0996077439 43.3048385047
                    77.1027348983 43.3041596826
                    77.1064119358 43.3041628646
                    77.1112946137 43.3044300136
                    77.1151743517 43.3047898764
                    77.1191711368 43.3041663465
                    77.1232925597 43.3041903376
                    77.1281797268 43.3052322396
                    77.1340378934 43.3040433821
                    77.1457107351 43.3043614401
                    77.1541859877 43.3055489469
                    77.1601528288 43.3068439102
                    77.1666927501 43.306854527
                    77.1696654415 43.3057610012
                    77.1744482898 43.3063077641
                    77.1781163787 43.307374748
                    77.1836638603 43.3073828183
                    77.1920667952 43.307894969
                    77.2003813071 43.3063898371
                    77.208973978 43.3049647446
                    77.2182158635 43.30442329
                    77.2247180777 43.3009776944
                    77.23138064 43.2982761887
                    77.2372304722 43.2990830621
                    77.2442318905 43.302025894
                    77.2497422768 43.3020261428
                </gml:posList>
            </gml:LineString>
            <dip>45</dip>
            <upperSeismoDepth>0</upperSeismoDepth>
            <lowerSeismoDepth>20</lowerSeismoDepth>
        </simpleFaultGeometry>
    </simpleFaultRupture>
</nrml>
